imshowmasks/__init__.py
imshowmasks/masks.py
imshowmasks-0.0.7.dist-info/LICENSE
imshowmasks-0.0.7.dist-info/METADATA
imshowmasks-0.0.7.dist-info/WHEEL
imshowmasks-0.0.7.dist-info/top_level.txt
imshowmasks-0.0.7.dist-info/RECORD
