Metadata-Version: 2.1
Name: imshowmasks
Version: 0.0.7
Summary: A slim package to handle and display binary masks in color over images shown with matplotlib.
Home-page: https://github.com/mbrammerloh/imshowmasks
Author: Malte Brammerloh
Author-email: m.brammerloh@gmail.com
License: UNKNOWN
Platform: UNKNOWN
Classifier: Programming Language :: Python :: 3
Classifier: License :: OSI Approved :: MIT License
Classifier: Operating System :: OS Independent
Requires-Python: >=3.6
